{"id": "R36", "name": "36 St", "longitude": "-74.003549", "latitude": "40.655144", "url": "", "service_maps": [{"group_id": "weekday_day", "routes": [{"id": "D", "color": "FF6319", "href": "https://demo.transiter.dev/systems/nycsubway/routes/D"}, {"id": "N", "color": "FCCC0A", "href": "https://demo.transiter.dev/systems/nycsubway/routes/N"}, {"id": "R", "color": "FCCC0A", "href": "https://demo.transiter.dev/systems/nycsubway/routes/R"}]}, {"group_id": "realtime", "routes": [{"id": "D", "color": "FF6319", "href": "https://demo.transiter.dev/systems/nycsubway/routes/D"}, {"id": "N", "color": "FCCC0A", "href": "https://demo.transiter.dev/systems/nycsubway/routes/N"}, {"id": "R", "color": "FCCC0A", "href": "https://demo.transiter.dev/systems/nycsubway/routes/R"}]}], "parent_stop": null, "child_stops": [], "directions": ["Coney Island - Bay Ridge", "Manhattan"], "alerts": [], "transfers": [], "stop_times": [{"arrival": {"time": 1652658880.0, "delay": null, "uncertainty": null}, "departure": {"time": 1652658880.0, "delay": null, "uncertainty": null}, "track": "F1", "future": true, "stop_sequence": 26, "direction": "Coney Island - Bay Ridge", "trip": {"id": "114000_N..S", "direction_id": true, "started_at": 1652641200.0, "updated_at": null, "delay": null, "vehicle": {"id": "1N 1900 DIT/STL"}, "route": {"id": "N", "color": "FCCC0A", "href": "https://demo.transiter.dev/systems/nycsubway/routes/N"}, "last_stop": {"id": "D43S", "name": "Coney Island-Stillwell Av", "href": "https://demo.transiter.dev/systems/nycsubway/stops/D43S"}, "href": "https://demo.transiter.dev/systems/nycsubway/routes/N/trips/114000_N..S"}}, {"arrival": {"time": 1652658997.0, "delay": null, "uncertainty": null}, "departure": {"time": 1652658997.0, "delay": null, "uncertainty": null}, "track": "F4", "future": true, "stop_sequence": 14, "direction": "Manhattan", "trip": {"id": "117000_D..N", "direction_id": false, "started_at": 1652643000.0, "updated_at": null, "delay": null, "vehicle": {"id": "1D 1930 STL/205"}, "route": {"id": "D", "color": "FF6319", "href": "https://demo.transiter.dev/systems/nycsubway/routes/D"}, "last_stop": {"id": "D01N", "name": "Norwood-205 St", "href": "https://demo.transiter.dev/systems/nycsubway/stops/D01N"}, "href": "https://demo.transiter.dev/systems/nycsubway/routes/D/trips/117000_D..N"}}, {"arrival": {"time": 1652659016.0, "delay": null, "uncertainty": null}, "departure": {"time": 1652659016.0, "delay": null, "uncertainty": null}, "track": "F4", "future": true, "stop_sequence": 12, "direction": "Manhattan", "trip": {"id": "116933_N..N", "direction_id": false, "started_at": 1652642960.0, "updated_at": null, "delay": null, "vehicle": {"id": "1N 1929 STL/DIT"}, "route": {"id": "N", "color": "FCCC0A", "href": "https://demo.transiter.dev/systems/nycsubway/routes/N"}, "last_stop": {"id": "R01N", "name": "Astoria-Ditmars Blvd", "href": "https://demo.transiter.dev/systems/nycsubway/stops/R01N"}, "href": "https://demo.transiter.dev/systems/nycsubway/routes/N/trips/116933_N..N"}}, {"arrival": {"time": 1652659038.0, "delay": null, "uncertainty": null}, "departure": {"time": 1652659038.0, "delay": null, "uncertainty": null}, "track": "F1", "future": true, "stop_sequence": 38, "direction": "Coney Island - Bay Ridge", "trip": {"id": "111400_R..S", "direction_id": true, "started_at": 1652639640.0, "updated_at": null, "delay": null, "vehicle": {"id": "1R 1834 CTL/9AV"}, "route": {"id": "R", "color": "FCCC0A", "href": "https://demo.transiter.dev/systems/nycsubway/routes/R"}, "last_stop": {"id": "B12S", "name": "9 Av", "href": "https://demo.transiter.dev/systems/nycsubway/stops/B12S"}, "href": "https://demo.transiter.dev/systems/nycsubway/routes/R/trips/111400_R..S"}}, {"arrival": {"time": 1652659383.0, "delay": null, "uncertainty": null}, "departure": {"time": 1652659383.0, "delay": null, "uncertainty": null}, "track": "F1", "future": true, "stop_sequence": 26, "direction": "Coney Island - Bay Ridge", "trip": {"id": "115200_N..S", "direction_id": true, "started_at": 1652641920.0, "updated_at": null, "delay": null, "vehicle": {"id": "1N 1912 DIT/STL"}, "route": {"id": "N", "color": "FCCC0A", "href": "https://demo.transiter.dev/systems/nycsubway/routes/N"}, "last_stop": {"id": "D43S", "name": "Coney Island-Stillwell Av", "href": "https://demo.transiter.dev/systems/nycsubway/stops/D43S"}, "href": "https://demo.transiter.dev/systems/nycsubway/routes/N/trips/115200_N..S"}}, {"arrival": {"time": 1652659442.0, "delay": null, "uncertainty": null}, "departure": {"time": 1652659442.0, "delay": null, "uncertainty": null}, "track": "F1", "future": true, "stop_sequence": 38, "direction": "Coney Island - Bay Ridge", "trip": {"id": "112600_R..S", "direction_id": true, "started_at": 1652640360.0, "updated_at": null, "delay": null, "vehicle": {"id": "1R 1846 CTL/9AV"}, "route": {"id": "R", "color": "FCCC0A", "href": "https://demo.transiter.dev/systems/nycsubway/routes/R"}, "last_stop": {"id": "B12S", "name": "9 Av", "href": "https://demo.transiter.dev/systems/nycsubway/stops/B12S"}, "href": "https://demo.transiter.dev/systems/nycsubway/routes/R/trips/112600_R..S"}}, {"arrival": {"time": 1652659650.0, "delay": null, "uncertainty": null}, "departure": {"time": 1652659650.0, "delay": null, "uncertainty": null}, "track": "F2", "future": true, "stop_sequence": 2, "direction": "Manhattan", "trip": {"id": "120350_R..N", "direction_id": false, "started_at": 1652645010.0, "updated_at": null, "delay": null, "vehicle": null, "route": {"id": "R", "color": "FCCC0A", "href": "https://demo.transiter.dev/systems/nycsubway/routes/R"}, "last_stop": {"id": "G08N", "name": "Forest Hills-71 Av", "href": "https://demo.transiter.dev/systems/nycsubway/stops/G08N"}, "href": "https://demo.transiter.dev/systems/nycsubway/routes/R/trips/120350_R..N"}}, {"arrival": {"time": 1652659740.0, "delay": null, "uncertainty": null}, "departure": {"time": 1652659740.0, "delay": null, "uncertainty": null}, "track": "F2", "future": true, "stop_sequence": 1, "direction": "Manhattan", "trip": {"id": "120900_R..N", "direction_id": false, "started_at": 1652645340.0, "updated_at": null, "delay": null, "vehicle": null, "route": {"id": "R", "color": "FCCC0A", "href": "https://demo.transiter.dev/systems/nycsubway/routes/R"}, "last_stop": {"id": "G08N", "name": "Forest Hills-71 Av", "href": "https://demo.transiter.dev/systems/nycsubway/stops/G08N"}, "href": "https://demo.transiter.dev/systems/nycsubway/routes/R/trips/120900_R..N"}}, {"arrival": {"time": 1652659781.0, "delay": null, "uncertainty": null}, "departure": {"time": 1652659781.0, "delay": null, "uncertainty": null}, "track": "F4", "future": true, "stop_sequence": 14, "direction": "Manhattan", "trip": {"id": "118505_D..N", "direction_id": false, "started_at": 1652643903.0, "updated_at": null, "delay": null, "vehicle": {"id": "1D 1945 STL/205"}, "route": {"id": "D", "color": "FF6319", "href": "https://demo.transiter.dev/systems/nycsubway/routes/D"}, "last_stop": {"id": "D01N", "name": "Norwood-205 St", "href": "https://demo.transiter.dev/systems/nycsubway/stops/D01N"}, "href": "https://demo.transiter.dev/systems/nycsubway/routes/D/trips/118505_D..N"}}, {"arrival": {"time": 1652659817.0, "delay": null, "uncertainty": null}, "departure": {"time": 1652659817.0, "delay": null, "uncertainty": null}, "track": "F3", "future": true, "stop_sequence": 22, "direction": "Coney Island - Bay Ridge", "trip": {"id": "114963_D..S", "direction_id": true, "started_at": 1652641778.0, "updated_at": null, "delay": null, "vehicle": {"id": "1D 1909+ BPK/STL"}, "route": {"id": "D", "color": "FF6319", "href": "https://demo.transiter.dev/systems/nycsubway/routes/D"}, "last_stop": {"id": "D43S", "name": "Coney Island-Stillwell Av", "href": "https://demo.transiter.dev/systems/nycsubway/stops/D43S"}, "href": "https://demo.transiter.dev/systems/nycsubway/routes/D/trips/114963_D..S"}}, {"arrival": {"time": 1652659937.0, "delay": null, "uncertainty": null}, "departure": {"time": 1652659937.0, "delay": null, "uncertainty": null}, "track": "F4", "future": true, "stop_sequence": 12, "direction": "Manhattan", "trip": {"id": "118708_N..N", "direction_id": false, "started_at": 1652644025.0, "updated_at": null, "delay": null, "vehicle": {"id": "1N 1947 STL/DIT"}, "route": {"id": "N", "color": "FCCC0A", "href": "https://demo.transiter.dev/systems/nycsubway/routes/N"}, "last_stop": {"id": "R01N", "name": "Astoria-Ditmars Blvd", "href": "https://demo.transiter.dev/systems/nycsubway/stops/R01N"}, "href": "https://demo.transiter.dev/systems/nycsubway/routes/N/trips/118708_N..N"}}, {"arrival": {"time": 1652660284.0, "delay": null, "uncertainty": null}, "departure": {"time": 1652660284.0, "delay": null, "uncertainty": null}, "track": "F1", "future": true, "stop_sequence": 26, "direction": "Coney Island - Bay Ridge", "trip": {"id": "116490_N..S", "direction_id": true, "started_at": 1652642694.0, "updated_at": null, "delay": null, "vehicle": {"id": "1N 1924 DIT/STL"}, "route": {"id": "N", "color": "FCCC0A", "href": "https://demo.transiter.dev/systems/nycsubway/routes/N"}, "last_stop": {"id": "D43S", "name": "Coney Island-Stillwell Av", "href": "https://demo.transiter.dev/systems/nycsubway/stops/D43S"}, "href": "https://demo.transiter.dev/systems/nycsubway/routes/N/trips/116490_N..S"}}, {"arrival": {"time": 1652660327.0, "delay": null, "uncertainty": null}, "departure": {"time": 1652660327.0, "delay": null, "uncertainty": null}, "track": "F3", "future": true, "stop_sequence": 22, "direction": "Coney Island - Bay Ridge", "trip": {"id": "116150_D..S", "direction_id": true, "started_at": 1652642490.0, "updated_at": null, "delay": null, "vehicle": {"id": "1D 1921+ BPK/STL"}, "route": {"id": "D", "color": "FF6319", "href": "https://demo.transiter.dev/systems/nycsubway/routes/D"}, "last_stop": {"id": "D43S", "name": "Coney Island-Stillwell Av", "href": "https://demo.transiter.dev/systems/nycsubway/stops/D43S"}, "href": "https://demo.transiter.dev/systems/nycsubway/routes/D/trips/116150_D..S"}}, {"arrival": {"time": 1652660370.0, "delay": null, "uncertainty": null}, "departure": {"time": 1652660370.0, "delay": null, "uncertainty": null}, "track": "F2", "future": true, "stop_sequence": 2, "direction": "Manhattan", "trip": {"id": "121550_R..N", "direction_id": false, "started_at": 1652645730.0, "updated_at": null, "delay": null, "vehicle": null, "route": {"id": "R", "color": "FCCC0A", "href": "https://demo.transiter.dev/systems/nycsubway/routes/R"}, "last_stop": {"id": "G08N", "name": "Forest Hills-71 Av", "href": "https://demo.transiter.dev/systems/nycsubway/stops/G08N"}, "href": "https://demo.transiter.dev/systems/nycsubway/routes/R/trips/121550_R..N"}}, {"arrival": {"time": 1652660456.0, "delay": null, "uncertainty": null}, "departure": {"time": 1652660456.0, "delay": null, "uncertainty": null}, "track": "F1", "future": true, "stop_sequence": 36, "direction": "Coney Island - Bay Ridge", "trip": {"id": "114300_R..S", "direction_id": true, "started_at": 1652641380.0, "updated_at": null, "delay": null, "vehicle": {"id": "1R 1904 CTL/9AV"}, "route": {"id": "R", "color": "FCCC0A", "href": "https://demo.transiter.dev/systems/nycsubway/routes/R"}, "last_stop": {"id": "B12S", "name": "9 Av", "href": "https://demo.transiter.dev/systems/nycsubway/stops/B12S"}, "href": "https://demo.transiter.dev/systems/nycsubway/routes/R/trips/114300_R..S"}}, {"arrival": {"time": 1652660730.0, "delay": null, "uncertainty": null}, "departure": {"time": 1652660730.0, "delay": null, "uncertainty": null}, "track": "F4", "future": true, "stop_sequence": 12, "direction": "Manhattan", "trip": {"id": "119900_N..N", "direction_id": false, "started_at": 1652644740.0, "updated_at": null, "delay": null, "vehicle": null, "route": {"id": "N", "color": "FCCC0A", "href": "https://demo.transiter.dev/systems/nycsubway/routes/N"}, "last_stop": {"id": "R01N", "name": "Astoria-Ditmars Blvd", "href": "https://demo.transiter.dev/systems/nycsubway/stops/R01N"}, "href": "https://demo.transiter.dev/systems/nycsubway/routes/N/trips/119900_N..N"}}, {"arrival": {"time": 1652660820.0, "delay": null, "uncertainty": null}, "departure": {"time": 1652660820.0, "delay": null, "uncertainty": null}, "track": "F4", "future": true, "stop_sequence": 14, "direction": "Manhattan", "trip": {"id": "120000_D..N", "direction_id": false, "started_at": 1652644800.0, "updated_at": null, "delay": null, "vehicle": null, "route": {"id": "D", "color": "FF6319", "href": "https://demo.transiter.dev/systems/nycsubway/routes/D"}, "last_stop": {"id": "D01N", "name": "Norwood-205 St", "href": "https://demo.transiter.dev/systems/nycsubway/stops/D01N"}, "href": "https://demo.transiter.dev/systems/nycsubway/routes/D/trips/120000_D..N"}}, {"arrival": {"time": 1652660971.0, "delay": null, "uncertainty": null}, "departure": {"time": 1652660971.0, "delay": null, "uncertainty": null}, "track": "F3", "future": true, "stop_sequence": 22, "direction": "Coney Island - Bay Ridge", "trip": {"id": "117350_D..S", "direction_id": true, "started_at": 1652643210.0, "updated_at": null, "delay": null, "vehicle": {"id": "1D 1933+ BPK/STL"}, "route": {"id": "D", "color": "FF6319", "href": "https://demo.transiter.dev/systems/nycsubway/routes/D"}, "last_stop": {"id": "D43S", "name": "Coney Island-Stillwell Av", "href": "https://demo.transiter.dev/systems/nycsubway/stops/D43S"}, "href": "https://demo.transiter.dev/systems/nycsubway/routes/D/trips/117350_D..S"}}, {"arrival": {"time": 1652661090.0, "delay": null, "uncertainty": null}, "departure": {"time": 1652661090.0, "delay": null, "uncertainty": null}, "track": "F2", "future": true, "stop_sequence": 2, "direction": "Manhattan", "trip": {"id": "122750_R..N", "direction_id": false, "started_at": 1652646450.0, "updated_at": null, "delay": null, "vehicle": null, "route": {"id": "R", "color": "FCCC0A", "href": "https://demo.transiter.dev/systems/nycsubway/routes/R"}, "last_stop": {"id": "G08N", "name": "Forest Hills-71 Av", "href": "https://demo.transiter.dev/systems/nycsubway/stops/G08N"}, "href": "https://demo.transiter.dev/systems/nycsubway/routes/R/trips/122750_R..N"}}, {"arrival": {"time": 1652661396.0, "delay": null, "uncertainty": null}, "departure": {"time": 1652661396.0, "delay": null, "uncertainty": null}, "track": "F1", "future": true, "stop_sequence": 25, "direction": "Coney Island - Bay Ridge", "trip": {"id": "118000_N..S", "direction_id": true, "started_at": 1652643600.0, "updated_at": null, "delay": null, "vehicle": {"id": "1N 1936 DIT/STL"}, "route": {"id": "N", "color": "FCCC0A", "href": "https://demo.transiter.dev/systems/nycsubway/routes/N"}, "last_stop": {"id": "D43S", "name": "Coney Island-Stillwell Av", "href": "https://demo.transiter.dev/systems/nycsubway/stops/D43S"}, "href": "https://demo.transiter.dev/systems/nycsubway/routes/N/trips/118000_N..S"}}, {"arrival": {"time": 1652661450.0, "delay": null, "uncertainty": null}, "departure": {"time": 1652661450.0, "delay": null, "uncertainty": null}, "track": "F4", "future": true, "stop_sequence": 12, "direction": "Manhattan", "trip": {"id": "121100_N..N", "direction_id": false, "started_at": 1652645460.0, "updated_at": null, "delay": null, "vehicle": null, "route": {"id": "N", "color": "FCCC0A", "href": "https://demo.transiter.dev/systems/nycsubway/routes/N"}, "last_stop": {"id": "R01N", "name": "Astoria-Ditmars Blvd", "href": "https://demo.transiter.dev/systems/nycsubway/stops/R01N"}, "href": "https://demo.transiter.dev/systems/nycsubway/routes/N/trips/121100_N..N"}}, {"arrival": {"time": 1652661720.0, "delay": null, "uncertainty": null}, "departure": {"time": 1652661720.0, "delay": null, "uncertainty": null}, "track": "F4", "future": true, "stop_sequence": 14, "direction": "Manhattan", "trip": {"id": "121500_D..N", "direction_id": false, "started_at": 1652645700.0, "updated_at": null, "delay": null, "vehicle": null, "route": {"id": "D", "color": "FF6319", "href": "https://demo.transiter.dev/systems/nycsubway/routes/D"}, "last_stop": {"id": "D01N", "name": "Norwood-205 St", "href": "https://demo.transiter.dev/systems/nycsubway/stops/D01N"}, "href": "https://demo.transiter.dev/systems/nycsubway/routes/D/trips/121500_D..N"}}, {"arrival": {"time": 1652661810.0, "delay": null, "uncertainty": null}, "departure": {"time": 1652661810.0, "delay": null, "uncertainty": null}, "track": "F2", "future": true, "stop_sequence": 2, "direction": "Manhattan", "trip": {"id": "123950_R..N", "direction_id": false, "started_at": 1652647170.0, "updated_at": null, "delay": null, "vehicle": null, "route": {"id": "R", "color": "FCCC0A", "href": "https://demo.transiter.dev/systems/nycsubway/routes/R"}, "last_stop": {"id": "G08N", "name": "Forest Hills-71 Av", "href": "https://demo.transiter.dev/systems/nycsubway/stops/G08N"}, "href": "https://demo.transiter.dev/systems/nycsubway/routes/R/trips/123950_R..N"}}, {"arrival": {"time": 1652661852.0, "delay": null, "uncertainty": null}, "departure": {"time": 1652661852.0, "delay": null, "uncertainty": null}, "track": "F1", "future": true, "stop_sequence": 26, "direction": "Coney Island - Bay Ridge", "trip": {"id": "118898_N..S", "direction_id": true, "started_at": 1652644139.0, "updated_at": null, "delay": null, "vehicle": {"id": "1N 1948 DIT/STL"}, "route": {"id": "N", "color": "FCCC0A", "href": "https://demo.transiter.dev/systems/nycsubway/routes/N"}, "last_stop": {"id": "D43S", "name": "Coney Island-Stillwell Av", "href": "https://demo.transiter.dev/systems/nycsubway/stops/D43S"}, "href": "https://demo.transiter.dev/systems/nycsubway/routes/N/trips/118898_N..S"}}, {"arrival": {"time": 1652662101.0, "delay": null, "uncertainty": null}, "departure": {"time": 1652662101.0, "delay": null, "uncertainty": null}, "track": "F1", "future": true, "stop_sequence": 38, "direction": "Coney Island - Bay Ridge", "trip": {"id": "116300_R..S", "direction_id": true, "started_at": 1652642580.0, "updated_at": null, "delay": null, "vehicle": {"id": "1R 1922 CTL/9AV"}, "route": {"id": "R", "color": "FCCC0A", "href": "https://demo.transiter.dev/systems/nycsubway/routes/R"}, "last_stop": {"id": "B12S", "name": "9 Av", "href": "https://demo.transiter.dev/systems/nycsubway/stops/B12S"}, "href": "https://demo.transiter.dev/systems/nycsubway/routes/R/trips/116300_R..S"}}, {"arrival": {"time": 1652662170.0, "delay": null, "uncertainty": null}, "departure": {"time": 1652662170.0, "delay": null, "uncertainty": null}, "track": "F4", "future": true, "stop_sequence": 12, "direction": "Manhattan", "trip": {"id": "122300_N..N", "direction_id": false, "started_at": 1652646180.0, "updated_at": null, "delay": null, "vehicle": null, "route": {"id": "N", "color": "FCCC0A", "href": "https://demo.transiter.dev/systems/nycsubway/routes/N"}, "last_stop": {"id": "R01N", "name": "Astoria-Ditmars Blvd", "href": "https://demo.transiter.dev/systems/nycsubway/stops/R01N"}, "href": "https://demo.transiter.dev/systems/nycsubway/routes/N/trips/122300_N..N"}}, {"arrival": {"time": 1652662230.0, "delay": null, "uncertainty": null}, "departure": {"time": 1652662230.0, "delay": null, "uncertainty": null}, "track": "F3", "future": true, "stop_sequence": 23, "direction": "Coney Island - Bay Ridge", "trip": {"id": "118765_D..S", "direction_id": true, "started_at": 1652644059.0, "updated_at": null, "delay": null, "vehicle": {"id": "1D 1947+ 205/STL"}, "route": {"id": "D", "color": "FF6319", "href": "https://demo.transiter.dev/systems/nycsubway/routes/D"}, "last_stop": {"id": "D43S", "name": "Coney Island-Stillwell Av", "href": "https://demo.transiter.dev/systems/nycsubway/stops/D43S"}, "href": "https://demo.transiter.dev/systems/nycsubway/routes/D/trips/118765_D..S"}}, {"arrival": {"time": 1652662465.0, "delay": null, "uncertainty": null}, "departure": {"time": 1652662465.0, "delay": null, "uncertainty": null}, "track": "F1", "future": true, "stop_sequence": 26, "direction": "Coney Island - Bay Ridge", "trip": {"id": "120000_N..S", "direction_id": true, "started_at": 1652644800.0, "updated_at": null, "delay": null, "vehicle": null, "route": {"id": "N", "color": "FCCC0A", "href": "https://demo.transiter.dev/systems/nycsubway/routes/N"}, "last_stop": {"id": "D43S", "name": "Coney Island-Stillwell Av", "href": "https://demo.transiter.dev/systems/nycsubway/stops/D43S"}, "href": "https://demo.transiter.dev/systems/nycsubway/routes/N/trips/120000_N..S"}}, {"arrival": {"time": 1652662530.0, "delay": null, "uncertainty": null}, "departure": {"time": 1652662530.0, "delay": null, "uncertainty": null}, "track": "F2", "future": true, "stop_sequence": 2, "direction": "Manhattan", "trip": {"id": "125150_R..N", "direction_id": false, "started_at": 1652647890.0, "updated_at": null, "delay": null, "vehicle": null, "route": {"id": "R", "color": "FCCC0A", "href": "https://demo.transiter.dev/systems/nycsubway/routes/R"}, "last_stop": {"id": "G08N", "name": "Forest Hills-71 Av", "href": "https://demo.transiter.dev/systems/nycsubway/stops/G08N"}, "href": "https://demo.transiter.dev/systems/nycsubway/routes/R/trips/125150_R..N"}}, {"arrival": {"time": 1652662620.0, "delay": null, "uncertainty": null}, "departure": {"time": 1652662620.0, "delay": null, "uncertainty": null}, "track": "F4", "future": true, "stop_sequence": 14, "direction": "Manhattan", "trip": {"id": "123000_D..N", "direction_id": false, "started_at": 1652646600.0, "updated_at": null, "delay": null, "vehicle": null, "route": {"id": "D", "color": "FF6319", "href": "https://demo.transiter.dev/systems/nycsubway/routes/D"}, "last_stop": {"id": "D01N", "name": "Norwood-205 St", "href": "https://demo.transiter.dev/systems/nycsubway/stops/D01N"}, "href": "https://demo.transiter.dev/systems/nycsubway/routes/D/trips/123000_D..N"}}, {"arrival": {"time": 1652662814.0, "delay": null, "uncertainty": null}, "departure": {"time": 1652662814.0, "delay": null, "uncertainty": null}, "track": "F1", "future": true, "stop_sequence": 38, "direction": "Coney Island - Bay Ridge", "trip": {"id": "117400_R..S", "direction_id": true, "started_at": 1652643240.0, "updated_at": null, "delay": null, "vehicle": {"id": "1R 1934 CTL/9AV"}, "route": {"id": "R", "color": "FCCC0A", "href": "https://demo.transiter.dev/systems/nycsubway/routes/R"}, "last_stop": {"id": "B12S", "name": "9 Av", "href": "https://demo.transiter.dev/systems/nycsubway/stops/B12S"}, "href": "https://demo.transiter.dev/systems/nycsubway/routes/R/trips/117400_R..S"}}, {"arrival": {"time": 1652662890.0, "delay": null, "uncertainty": null}, "departure": {"time": 1652662890.0, "delay": null, "uncertainty": null}, "track": "F4", "future": true, "stop_sequence": 12, "direction": "Manhattan", "trip": {"id": "123500_N..N", "direction_id": false, "started_at": 1652646900.0, "updated_at": null, "delay": null, "vehicle": null, "route": {"id": "N", "color": "FCCC0A", "href": "https://demo.transiter.dev/systems/nycsubway/routes/N"}, "last_stop": {"id": "R01N", "name": "Astoria-Ditmars Blvd", "href": "https://demo.transiter.dev/systems/nycsubway/stops/R01N"}, "href": "https://demo.transiter.dev/systems/nycsubway/routes/N/trips/123500_N..N"}}, {"arrival": {"time": 1652663155.0, "delay": null, "uncertainty": null}, "departure": {"time": 1652663155.0, "delay": null, "uncertainty": null}, "track": "F1", "future": true, "stop_sequence": 26, "direction": "Coney Island - Bay Ridge", "trip": {"id": "121200_N..S", "direction_id": true, "started_at": 1652645520.0, "updated_at": null, "delay": null, "vehicle": null, "route": {"id": "N", "color": "FCCC0A", "href": "https://demo.transiter.dev/systems/nycsubway/routes/N"}, "last_stop": {"id": "D43S", "name": "Coney Island-Stillwell Av", "href": "https://demo.transiter.dev/systems/nycsubway/stops/D43S"}, "href": "https://demo.transiter.dev/systems/nycsubway/routes/N/trips/121200_N..S"}}, {"arrival": {"time": 1652663310.0, "delay": null, "uncertainty": null}, "departure": {"time": 1652663310.0, "delay": null, "uncertainty": null}, "track": "F3", "future": true, "stop_sequence": 23, "direction": "Coney Island - Bay Ridge", "trip": {"id": "120550_D..S", "direction_id": true, "started_at": 1652645130.0, "updated_at": null, "delay": null, "vehicle": null, "route": {"id": "D", "color": "FF6319", "href": "https://demo.transiter.dev/systems/nycsubway/routes/D"}, "last_stop": {"id": "D43S", "name": "Coney Island-Stillwell Av", "href": "https://demo.transiter.dev/systems/nycsubway/stops/D43S"}, "href": "https://demo.transiter.dev/systems/nycsubway/routes/D/trips/120550_D..S"}}, {"arrival": {"time": 1652663441.0, "delay": null, "uncertainty": null}, "departure": {"time": 1652663441.0, "delay": null, "uncertainty": null}, "track": "F1", "future": true, "stop_sequence": 38, "direction": "Coney Island - Bay Ridge", "trip": {"id": "119200_R..S", "direction_id": true, "started_at": 1652644320.0, "updated_at": null, "delay": null, "vehicle": {"id": "1R 1952 CTL/9AV"}, "route": {"id": "R", "color": "FCCC0A", "href": "https://demo.transiter.dev/systems/nycsubway/routes/R"}, "last_stop": {"id": "B12S", "name": "9 Av", "href": "https://demo.transiter.dev/systems/nycsubway/stops/B12S"}, "href": "https://demo.transiter.dev/systems/nycsubway/routes/R/trips/119200_R..S"}}, {"arrival": {"time": 1652663520.0, "delay": null, "uncertainty": null}, "departure": {"time": 1652663520.0, "delay": null, "uncertainty": null}, "track": "F4", "future": true, "stop_sequence": 14, "direction": "Manhattan", "trip": {"id": "124500_D..N", "direction_id": false, "started_at": 1652647500.0, "updated_at": null, "delay": null, "vehicle": null, "route": {"id": "D", "color": "FF6319", "href": "https://demo.transiter.dev/systems/nycsubway/routes/D"}, "last_stop": {"id": "D01N", "name": "Norwood-205 St", "href": "https://demo.transiter.dev/systems/nycsubway/stops/D01N"}, "href": "https://demo.transiter.dev/systems/nycsubway/routes/D/trips/124500_D..N"}}, {"arrival": {"time": 1652663610.0, "delay": null, "uncertainty": null}, "departure": {"time": 1652663610.0, "delay": null, "uncertainty": null}, "track": "F4", "future": true, "stop_sequence": 12, "direction": "Manhattan", "trip": {"id": "124700_N..N", "direction_id": false, "started_at": 1652647620.0, "updated_at": null, "delay": null, "vehicle": null, "route": {"id": "N", "color": "FCCC0A", "href": "https://demo.transiter.dev/systems/nycsubway/routes/N"}, "last_stop": {"id": "R01N", "name": "Astoria-Ditmars Blvd", "href": "https://demo.transiter.dev/systems/nycsubway/stops/R01N"}, "href": "https://demo.transiter.dev/systems/nycsubway/routes/N/trips/124700_N..N"}}, {"arrival": {"time": 1652663905.0, "delay": null, "uncertainty": null}, "departure": {"time": 1652663905.0, "delay": null, "uncertainty": null}, "track": "F1", "future": true, "stop_sequence": 26, "direction": "Coney Island - Bay Ridge", "trip": {"id": "122500_N..S", "direction_id": true, "started_at": 1652646300.0, "updated_at": null, "delay": null, "vehicle": null, "route": {"id": "N", "color": "FCCC0A", "href": "https://demo.transiter.dev/systems/nycsubway/routes/N"}, "last_stop": {"id": "D43S", "name": "Coney Island-Stillwell Av", "href": "https://demo.transiter.dev/systems/nycsubway/stops/D43S"}, "href": "https://demo.transiter.dev/systems/nycsubway/routes/N/trips/122500_N..S"}}, {"arrival": {"time": 1652664030.0, "delay": null, "uncertainty": null}, "departure": {"time": 1652664030.0, "delay": null, "uncertainty": null}, "track": "F3", "future": true, "stop_sequence": 23, "direction": "Coney Island - Bay Ridge", "trip": {"id": "121750_D..S", "direction_id": true, "started_at": 1652645850.0, "updated_at": null, "delay": null, "vehicle": null, "route": {"id": "D", "color": "FF6319", "href": "https://demo.transiter.dev/systems/nycsubway/routes/D"}, "last_stop": {"id": "D43S", "name": "Coney Island-Stillwell Av", "href": "https://demo.transiter.dev/systems/nycsubway/stops/D43S"}, "href": "https://demo.transiter.dev/systems/nycsubway/routes/D/trips/121750_D..S"}}, {"arrival": {"time": 1652664420.0, "delay": null, "uncertainty": null}, "departure": {"time": 1652664420.0, "delay": null, "uncertainty": null}, "track": "F4", "future": true, "stop_sequence": 14, "direction": "Manhattan", "trip": {"id": "126000_D..N", "direction_id": false, "started_at": 1652648400.0, "updated_at": null, "delay": null, "vehicle": null, "route": {"id": "D", "color": "FF6319", "href": "https://demo.transiter.dev/systems/nycsubway/routes/D"}, "last_stop": {"id": "D01N", "name": "Norwood-205 St", "href": "https://demo.transiter.dev/systems/nycsubway/stops/D01N"}, "href": "https://demo.transiter.dev/systems/nycsubway/routes/D/trips/126000_D..N"}}, {"arrival": {"time": 1652664540.0, "delay": null, "uncertainty": null}, "departure": {"time": 1652664540.0, "delay": null, "uncertainty": null}, "track": "F1", "future": true, "stop_sequence": 38, "direction": "Coney Island - Bay Ridge", "trip": {"id": "121000_R..S", "direction_id": true, "started_at": 1652645400.0, "updated_at": null, "delay": null, "vehicle": null, "route": {"id": "R", "color": "FCCC0A", "href": "https://demo.transiter.dev/systems/nycsubway/routes/R"}, "last_stop": {"id": "B12S", "name": "9 Av", "href": "https://demo.transiter.dev/systems/nycsubway/stops/B12S"}, "href": "https://demo.transiter.dev/systems/nycsubway/routes/R/trips/121000_R..S"}}, {"arrival": {"time": 1652664655.0, "delay": null, "uncertainty": null}, "departure": {"time": 1652664655.0, "delay": null, "uncertainty": null}, "track": "F1", "future": true, "stop_sequence": 26, "direction": "Coney Island - Bay Ridge", "trip": {"id": "123700_N..S", "direction_id": true, "started_at": 1652647020.0, "updated_at": null, "delay": null, "vehicle": null, "route": {"id": "N", "color": "FCCC0A", "href": "https://demo.transiter.dev/systems/nycsubway/routes/N"}, "last_stop": {"id": "D43S", "name": "Coney Island-Stillwell Av", "href": "https://demo.transiter.dev/systems/nycsubway/stops/D43S"}, "href": "https://demo.transiter.dev/systems/nycsubway/routes/N/trips/123700_N..S"}}, {"arrival": {"time": 1652664750.0, "delay": null, "uncertainty": null}, "departure": {"time": 1652664750.0, "delay": null, "uncertainty": null}, "track": "F3", "future": true, "stop_sequence": 23, "direction": "Coney Island - Bay Ridge", "trip": {"id": "122950_D..S", "direction_id": true, "started_at": 1652646570.0, "updated_at": null, "delay": null, "vehicle": null, "route": {"id": "D", "color": "FF6319", "href": "https://demo.transiter.dev/systems/nycsubway/routes/D"}, "last_stop": {"id": "D43S", "name": "Coney Island-Stillwell Av", "href": "https://demo.transiter.dev/systems/nycsubway/stops/D43S"}, "href": "https://demo.transiter.dev/systems/nycsubway/routes/D/trips/122950_D..S"}}, {"arrival": {"time": 1652665260.0, "delay": null, "uncertainty": null}, "departure": {"time": 1652665260.0, "delay": null, "uncertainty": null}, "track": "F1", "future": true, "stop_sequence": 38, "direction": "Coney Island - Bay Ridge", "trip": {"id": "122200_R..S", "direction_id": true, "started_at": 1652646120.0, "updated_at": null, "delay": null, "vehicle": null, "route": {"id": "R", "color": "FCCC0A", "href": "https://demo.transiter.dev/systems/nycsubway/routes/R"}, "last_stop": {"id": "B12S", "name": "9 Av", "href": "https://demo.transiter.dev/systems/nycsubway/stops/B12S"}, "href": "https://demo.transiter.dev/systems/nycsubway/routes/R/trips/122200_R..S"}}, {"arrival": {"time": 1652665375.0, "delay": null, "uncertainty": null}, "departure": {"time": 1652665375.0, "delay": null, "uncertainty": null}, "track": "F1", "future": true, "stop_sequence": 26, "direction": "Coney Island - Bay Ridge", "trip": {"id": "124900_N..S", "direction_id": true, "started_at": 1652647740.0, "updated_at": null, "delay": null, "vehicle": null, "route": {"id": "N", "color": "FCCC0A", "href": "https://demo.transiter.dev/systems/nycsubway/routes/N"}, "last_stop": {"id": "D43S", "name": "Coney Island-Stillwell Av", "href": "https://demo.transiter.dev/systems/nycsubway/stops/D43S"}, "href": "https://demo.transiter.dev/systems/nycsubway/routes/N/trips/124900_N..S"}}, {"arrival": {"time": 1652665830.0, "delay": null, "uncertainty": null}, "departure": {"time": 1652665830.0, "delay": null, "uncertainty": null}, "track": "F3", "future": true, "stop_sequence": 23, "direction": "Coney Island - Bay Ridge", "trip": {"id": "124750_D..S", "direction_id": true, "started_at": 1652647650.0, "updated_at": null, "delay": null, "vehicle": null, "route": {"id": "D", "color": "FF6319", "href": "https://demo.transiter.dev/systems/nycsubway/routes/D"}, "last_stop": {"id": "D43S", "name": "Coney Island-Stillwell Av", "href": "https://demo.transiter.dev/systems/nycsubway/stops/D43S"}, "href": "https://demo.transiter.dev/systems/nycsubway/routes/D/trips/124750_D..S"}}, {"arrival": {"time": 1652666100.0, "delay": null, "uncertainty": null}, "departure": {"time": 1652666100.0, "delay": null, "uncertainty": null}, "track": "F1", "future": true, "stop_sequence": 38, "direction": "Coney Island - Bay Ridge", "trip": {"id": "123400_R..S", "direction_id": true, "started_at": 1652646840.0, "updated_at": null, "delay": null, "vehicle": null, "route": {"id": "R", "color": "FCCC0A", "href": "https://demo.transiter.dev/systems/nycsubway/routes/R"}, "last_stop": {"id": "B12S", "name": "9 Av", "href": "https://demo.transiter.dev/systems/nycsubway/stops/B12S"}, "href": "https://demo.transiter.dev/systems/nycsubway/routes/R/trips/123400_R..S"}}, {"arrival": {"time": 1652666790.0, "delay": null, "uncertainty": null}, "departure": {"time": 1652666790.0, "delay": null, "uncertainty": null}, "track": "F1", "future": true, "stop_sequence": 38, "direction": "Coney Island - Bay Ridge", "trip": {"id": "124600_R..S", "direction_id": true, "started_at": 1652647560.0, "updated_at": null, "delay": null, "vehicle": null, "route": {"id": "R", "color": "FCCC0A", "href": "https://demo.transiter.dev/systems/nycsubway/routes/R"}, "last_stop": {"id": "B12S", "name": "9 Av", "href": "https://demo.transiter.dev/systems/nycsubway/stops/B12S"}, "href": "https://demo.transiter.dev/systems/nycsubway/routes/R/trips/124600_R..S"}}]}